[
    {
        "image": "../../../../assets/home-image/portrait/Variant5 (1).webp",
        "title": "CIW Domiciliary Care Agency Set Up Package"
    },
    {
        "image": "../../../../assets/home-image/portrait/Variant6.webp",
        "title": "RQIA Domiciliary Care Agency Setup Package"
    },
    {
        "image": "../../../../assets/home-image/portrait/Default (1).webp",
        "title": "Domiciliary Care"
    },
    {
        "image": "../../../../assets/home-image/portrait/Variant2.webp",
        "title": "Supported Living"
    },
    {
        "image": "../../../../assets/home-image/portrait/Variant3.webp",
        "title": "Temporary Staffing Solutions"
    },
    {
        "image": "../../../../assets/home-image/portrait/Variant4.webp",
        "title": "Combined Care Agency"
    }
]